TRUNAJOD/discourse_markers.py
TRUNAJOD/emotions.py
TRUNAJOD/entity_grid.py
TRUNAJOD/givenness.py
TRUNAJOD/lexico_semantic_norms.py
TRUNAJOD/lexicosemantic_norms_espal.py
TRUNAJOD/semantic_measures.py
TRUNAJOD/spanish_emotion_lexicon.py
TRUNAJOD/surface_proxies.py
TRUNAJOD/syllabizer.py
TRUNAJOD/ttr.py
TRUNAJOD/utils.py
TRUNAJOD/verb_types.py
TRUNAJOD-0.1.1.dist-info/LICENSE
TRUNAJOD-0.1.1.dist-info/METADATA
TRUNAJOD-0.1.1.dist-info/WHEEL
TRUNAJOD-0.1.1.dist-info/top_level.txt
TRUNAJOD-0.1.1.dist-info/RECORD
