Metadata-Version: 2.1
Name: TRUNAJOD
Version: 0.1.1
Summary: A python lib for readability analyses.
Home-page: https://github.com/dpalmasan/TRUNAJOD2.0
Author: Diego Palma
Author-email: dipalma@udec.cl
License: MIT
Download-URL: https://github.com/dpalmasan/TRUNAJOD2.0/archive/refs/tags/v0.1.1.tar.gz
Project-URL: Documentation, https://trunajod20.readthedocs.io/en/latest/
Project-URL: Source Code, https://github.com/dpalmasan/TRUNAJOD2.0
Project-URL: Bug Tracker, https://github.com/dpalmasan/TRUNAJOD2.0/issues
Keywords: NLP,readability,entity grid,linguistics,nlp,text complexity
Platform: UNKNOWN
Classifier: Development Status :: 3 - Alpha
Classifier: Intended Audience :: Developers
Classifier: Topic :: Education :: Computer Aided Instruction (CAI)
Classifier: License :: OSI Approved :: MIT License
Classifier: Programming Language :: Python :: 3
Classifier: Programming Language :: Python :: 3.6
Classifier: Programming Language :: Python :: 3.7
Classifier: Programming Language :: Python :: 3.8
Classifier: Programming Language :: Python :: 3.9
Classifier: Operating System :: POSIX
Classifier: Operating System :: MacOS
Classifier: Operating System :: Unix
Classifier: Operating System :: Microsoft :: Windows
Requires-Python: >=3.6
Requires-Dist: spacy (>=2.3.2)
